[
    {
        "category": "상의",
        "id": 1001,
        "title": "상의1",
        "price": "50,000",
        "description": "상의 설명",
        "image": "./assets/image/Mtop1.png"
    },
    {
        "category": "상의",
        "id": 1002,
        "title": "상의2",
        "price": "50,000",
        "description": "상의 설명",
        "image": "./assets/image/Mtop2.png"
    },
    {
        "category": "상의",
        "id": 1003,
        "title": "상의3",
        "price": "50,000",
        "description": "상의 설명",
        "image": "./assets/image/Mtop3.png"
    },
    {
        "category": "상의",
        "id": 1004,
        "title": "상의1",
        "price": "50,000",
        "description": "상의 설명",
        "image": "./assets/image/Mtop1.png"
    },
    {
        "category": "상의",
        "id": 1005,
        "title": "상의2",
        "price": "50,000",
        "description": "상의 설명",
        "image": "./assets/image/Mtop2.png"
    },
    {
        "category": "상의",
        "id": 1006,
        "title": "상의3",
        "price": "50,000",
        "description": "상의 설명",
        "image": "./assets/image/Mtop3.png"
    },
    {
        "category": "상의",
        "id": 1007,
        "title": "상의1",
        "price": "50,000",
        "description": "상의 설명",
        "image": "./assets/image/Mtop1.png"
    },
    {
        "category": "상의",
        "id": 1008,
        "title": "상의2",
        "price": "50,000",
        "description": "상의 설명",
        "image": "./assets/image/Mtop2.png"
    },
    {
        "category": "상의",
        "id": 1009,
        "title": "상의3",
        "price": "50,000",
        "description": "상의 설명",
        "image": "./assets/image/Mtop3.png"
    },
    {
        "category": "상의",
        "id": 1010,
        "title": "상의1",
        "price": "50,000",
        "description": "상의 설명",
        "image": "./assets/image/Mtop1.png"
    },
    {
        "category": "상의",
        "id": 1011,
        "title": "상의2",
        "price": "50,000",
        "description": "상의 설명",
        "image": "./assets/image/Mtop2.png"
    },
    {
        "category": "상의",
        "id": 1012,
        "title": "상의3",
        "price": "50,000",
        "description": "상의 설명",
        "image": "./assets/image/Mtop3.png"
    },
    {
        "category": "상의",
        "id": 1013,
        "title": "상의1",
        "price": "50,000",
        "description": "상의 설명",
        "image": "./assets/image/Mtop1.png"
    },
    {
        "category": "상의",
        "id": 1014,
        "title": "상의2",
        "price": "50,000",
        "description": "상의 설명",
        "image": "./assets/image/Mtop2.png"
    },
    {
        "category": "상의",
        "id": 1015,
        "title": "상의3",
        "price": "50,000",
        "description": "상의 설명",
        "image": "./assets/image/Mtop3.png"
    },
    {
        "category": "상의",
        "id": 1016,
        "title": "상의1",
        "price": "50,000",
        "description": "상의 설명",
        "image": "./assets/image/Mtop1.png"
    },
    {
        "category": "상의",
        "id": 1017,
        "title": "상의2",
        "price": "50,000",
        "description": "상의 설명",
        "image": "./assets/image/Mtop2.png"
    },
    {
        "category": "상의",
        "id": 1018,
        "title": "상의3",
        "price": "50,000",
        "description": "상의 설명",
        "image": "./assets/image/Mtop3.png"
    },
    {
        "category": "하의",
        "id": 2001,
        "title": "하의1",
        "price": "50,000",
        "description": "하의 설명",
        "image": "./assets/image/Mbottom1.png"
    },
    {
        "category": "하의",
        "id": 2002,
        "title": "하의2",
        "price": "50,000",
        "description": "하의 설명",
        "image": "./assets/image/Mbottom1.png"
    },
    {
        "category": "하의",
        "id": 2003,
        "title": "하의3",
        "price": "50,000",
        "description": "하의 설명",
        "image": "./assets/image/Mbottom2.png"
    },
    {
        "category": "하의",
        "id": 2002,
        "title": "하의2",
        "price": "50,000",
        "description": "하의 설명",
        "image": "./assets/image/Mbottom1.png"
    },
    {
        "category": "하의",
        "id": 2003,
        "title": "하의3",
        "price": "50,000",
        "description": "하의 설명",
        "image": "./assets/image/Mbottom2.png"
    },
    {
        "category": "하의",
        "id": 2004,
        "title": "하의2",
        "price": "50,000",
        "description": "하의 설명",
        "image": "./assets/image/Mbottom1.png"
    },
    {
        "category": "하의",
        "id": 2005,
        "title": "하의3",
        "price": "50,000",
        "description": "하의 설명",
        "image": "./assets/image/Mbottom2.png"
    },
    {
        "category": "하의",
        "id": 2006,
        "title": "하의2",
        "price": "50,000",
        "description": "하의 설명",
        "image": "./assets/image/Mbottom1.png"
    },
    {
        "category": "하의",
        "id": 2007,
        "title": "하의3",
        "price": "50,000",
        "description": "하의 설명",
        "image": "./assets/image/Mbottom2.png"
    },
    {
        "category": "재킷",
        "id": 3001,
        "title": "재킷1",
        "price": "50,000",
        "description": "재킷 설명",
        "image": "./assets/image/Mjackit1.png"
    },
    {
        "category": "재킷",
        "id": 3002,
        "title": "재킷2",
        "price": "50,000",
        "description": "재킷 설명",
        "image": "./assets/image/Mjackit2.png"
    },
    {
        "category": "재킷",
        "id": 3003,
        "title": "재킷3",
        "price": "50,000",
        "description": "재킷 설명",
        "image": "./assets/image/Mjackit1.png"
    },
    {
        "category": "재킷",
        "id": 3004,
        "title": "재킷3",
        "price": "50,000",
        "description": "재킷 설명",
        "image": "./assets/image/Mjackit2.png"
    },
    {
        "category": "재킷",
        "id": 3005,
        "title": "재킷1",
        "price": "50,000",
        "description": "재킷 설명",
        "image": "./assets/image/Mjackit1.png"
    },
    {
        "category": "재킷",
        "id": 3006,
        "title": "재킷2",
        "price": "50,000",
        "description": "재킷 설명",
        "image": "./assets/image/Mjackit2.png"
    },
    {
        "category": "재킷",
        "id": 3007,
        "title": "재킷3",
        "price": "50,000",
        "description": "재킷 설명",
        "image": "./assets/image/Mjackit1.png"
    },
    {
        "category": "재킷",
        "id": 3008,
        "title": "재킷3",
        "price": "50,000",
        "description": "재킷 설명",
        "image": "./assets/image/Mjackit2.png"
    },
    {
        "category": "재킷",
        "id": 3009,
        "title": "재킷1",
        "price": "50,000",
        "description": "재킷 설명",
        "image": "./assets/image/Mjackit1.png"
    },
    {
        "category": "재킷",
        "id": 3010,
        "title": "재킷2",
        "price": "50,000",
        "description": "재킷 설명",
        "image": "./assets/image/Mjackit2.png"
    },
    {
        "category": "재킷",
        "id": 3011,
        "title": "재킷3",
        "price": "50,000",
        "description": "재킷 설명",
        "image": "./assets/image/Mjackit1.png"
    },
    {
        "category": "재킷",
        "id": 3012,
        "title": "재킷3",
        "price": "50,000",
        "description": "재킷 설명",
        "image": "./assets/image/Mjackit2.png"
    },
    {
        "category": "용품",
        "id": 4001,
        "title": "용품1",
        "price": "50,000",
        "description": "용품 설명",
        "image": "./assets/image/Mcap1.png"
    },
    {
        "category": "용품",
        "id": 4002,
        "title": "용품2",
        "price": "50,000",
        "description": "용품 설명",
        "image": "./assets/image/Mcap2.png"
    },
    {
        "category": "용품",
        "id": 4003,
        "title": "용품3",
        "price": "50,000",
        "description": "용품 설명",
        "image": "./assets/image/Mcap1.png"
    },
    {
        "category": "용품",
        "id": 4004,
        "title": "용품2",
        "price": "50,000",
        "description": "용품 설명",
        "image": "./assets/image/Mcap2.png"
    },
    {
        "category": "용품",
        "id": 4005,
        "title": "용품1",
        "price": "50,000",
        "description": "용품 설명",
        "image": "./assets/image/Mcap1.png"
    },
    {
        "category": "용품",
        "id": 4006,
        "title": "용품2",
        "price": "50,000",
        "description": "용품 설명",
        "image": "./assets/image/Mcap2.png"
    },
    {
        "category": "용품",
        "id": 4007,
        "title": "용품3",
        "price": "50,000",
        "description": "용품 설명",
        "image": "./assets/image/Mcap1.png"
    },
    {
        "category": "용품",
        "id": 4008,
        "title": "용품2",
        "price": "50,000",
        "description": "용품 설명",
        "image": "./assets/image/Mcap2.png"
    },
    {
        "category": "용품",
        "id": 4009,
        "title": "용품1",
        "price": "50,000",
        "description": "용품 설명",
        "image": "./assets/image/Mcap1.png"
    },
    {
        "category": "용품",
        "id": 4010,
        "title": "용품2",
        "price": "50,000",
        "description": "용품 설명",
        "image": "./assets/image/Mcap2.png"
    },
    {
        "category": "용품",
        "id": 4011,
        "title": "용품3",
        "price": "50,000",
        "description": "용품 설명",
        "image": "./assets/image/Mcap1.png"
    },
    {
        "category": "용품",
        "id": 4012,
        "title": "용품2",
        "price": "50,000",
        "description": "용품 설명",
        "image": "./assets/image/Mcap2.png"
    },
    {
        "category": "용품",
        "id": 4013,
        "title": "용품1",
        "price": "50,000",
        "description": "용품 설명",
        "image": "./assets/image/Mcap1.png"
    },
    {
        "category": "용품",
        "id": 4014,
        "title": "용품2",
        "price": "50,000",
        "description": "용품 설명",
        "image": "./assets/image/Mcap2.png"
    },
    {
        "category": "용품",
        "id": 4015,
        "title": "용품3",
        "price": "50,000",
        "description": "용품 설명",
        "image": "./assets/image/Mcap1.png"
    },
    {
        "category": "용품",
        "id": 4016,
        "title": "용품2",
        "price": "50,000",
        "description": "용품 설명",
        "image": "./assets/image/Mcap2.png"
    },
    {
        "category": "용품",
        "id": 4017,
        "title": "용품1",
        "price": "50,000",
        "description": "용품 설명",
        "image": "./assets/image/Mcap1.png"
    },
    {
        "category": "용품",
        "id": 4018,
        "title": "용품2",
        "price": "50,000",
        "description": "용품 설명",
        "image": "./assets/image/Mcap2.png"
    },
    {
        "category": "용품",
        "id": 4019,
        "title": "용품3",
        "price": "50,000",
        "description": "용품 설명",
        "image": "./assets/image/Mcap1.png"
    },
    {
        "category": "용품",
        "id": 4020,
        "title": "용품2",
        "price": "50,000",
        "description": "용품 설명",
        "image": "./assets/image/Mcap2.png"
    }
]
